[
  {
    "question": "N2 + 3H2 ⇌ 2NH3 반응에서 평형상수는 [NH3]^2 / [N2][H2]^3 이다.",
    "type": "OX",
    "answer": "O"
  },
  {
    "question": "2SO2 + O2 ⇌ 2SO3 (발열반응)에서 온도를 낮추고 압력을 높이면 평형이 오른쪽으로 이동한다.",
    "type": "OX",
    "answer": "O"
  },
  {
    "question": "N2O4 ⇌ 2NO2 (흡열반응)에서 온도를 높이고 압력을 낮추면 평형이 왼쪽으로 이동한다.",
    "type": "OX",
    "answer": "X"
  },
  {
    "question": "2H2 + O2 ⇌ 2H2O (발열반응)에서 온도를 낮추고 압력을 높이면 평형이 왼쪽으로 이동한다.",
    "type": "OX",
    "answer": "X"
  },
  {
    "question": "2SO3 ⇌ 2SO2 + O2 (흡열반응)에서 온도를 높이고 압력을 낮추면 평형이 오른쪽으로 이동한다.",
    "type": "OX",
    "answer": "O"
  },
  {
    "question": "CO + H2O ⇌ CO2 + H2 (흡열반응)에서 온도를 높이고 압력을 높이면 평형이 오른쪽으로 이동한다.",
    "type": "OX",
    "answer": "O"
  },
  {
    "question": "2NO + O2 ⇌ 2NO2 (발열반응)에서 온도를 높이고 압력을 낮추면 평형이 왼쪽으로 이동한다.",
    "type": "OX",
    "answer": "O"
  },
  {
    "question": "2NO2 ⇌ 2NO + O2 (흡열반응)에서 온도를 높이고 압력을 낮추면 평형이 왼쪽으로 이동한다.",
    "type": "OX",
    "answer": "X"
  },
  {
    "question": "2NH3 ⇌ N2 + 3H2 (흡열반응)에서 온도를 낮추고 압력을 높이면 평형이 오른쪽으로 이동한다.",
    "type": "OX",
    "answer": "X"
  },
  {
    "question": "2H2O ⇌ 2H2 + O2 (흡열반응)에서 온도를 높이고 압력을 낮추면 평형이 오른쪽으로 이동한다.",
    "type": "OX",
    "answer": "O"
  }
]